Workbook

Sheet Transactions
A1: Date | B1: Business | C1: Type | D1: Category | E1: Amount (INR) | F1: Month
A2: 2026-03-18 | B2: Cafe | C2: Income | D2: Sales | E2: 14250 | F2: =TEXT(A2,"mmm-yy")
A3: 2026-03-18 | B3: Travel | C3: Expense | D3: Fuel | E3: 3200 | F3: =TEXT(A3,"mmm-yy")
A4: 2026-03-17 | B4: Textile | C4: Income | D4: Wholesale | E4: 22100 | F4: =TEXT(A4,"mmm-yy")
A5: 2026-03-17 | B5: Hardware | C5: Expense | D5: Inventory | E5: 8900 | F5: =TEXT(A5,"mmm-yy")
A6: 2026-03-16 | B6: Cafe | C6: Expense | D6: Supplies | E6: 2800 | F6: =TEXT(A6,"mmm-yy")
A7: 2026-03-15 | B7: Travel | C7: Income | D7: Packages | E7: 18100 | F7: =TEXT(A7,"mmm-yy")
A8: 2026-03-14 | B8: Hardware | C8: Income | D8: Retail | E8: 26400 | F8: =TEXT(A8,"mmm-yy")
A9: 2026-03-14 | B9: Textile | C9: Expense | D9: Logistics | E9: 11900 | F9: =TEXT(A9,"mmm-yy")
A10: 2026-02-28 | B10: Cafe | C10: Income | D10: Sales | E10: 12600 | F10: =TEXT(A10,"mmm-yy")
A11: 2026-02-25 | B11: Travel | C11: Expense | D11: Marketing | E11: 4600 | F11: =TEXT(A11,"mmm-yy")
A12: 2026-02-19 | B12: Textile | C12: Income | D12: Wholesale | E12: 19700 | F12: =TEXT(A12,"mmm-yy")
A13: 2026-02-13 | B13: Hardware | C13: Expense | D13: Rent | E13: 7100 | F13: =TEXT(A13,"mmm-yy")
... A21: 2025-12-02 | B21: Hardware | C21: Expense | D21: Inventory | E21: 6200 | F21: =TEXT(A21,"mmm-yy")

Sheet Summary
A1: Expense & Profit Tracker - Advanced Summary
A3: KPI | B3: Value | D3: Business Comparison
A4: Total Revenue | B4: =SUMIFS(Transactions!E:E,Transactions!C:C,"Income") | D4: Business | E4: Income (INR) | F4: Expense (INR) | G4: Profit (INR)
A5: Total Expenses | B5: =SUMIFS(Transactions!E:E,Transactions!C:C,"Expense") | D5: Cafe | E5: =SUMIFS(Transactions!E:E,Transactions!B:B,D5,Transactions!C:C,"Income") | F5: =SUMIFS(Transactions!E:E,Transactions!B:B,D5,Transactions!C:C,"Expense") | G5: =E5-F5
A6: Net Profit | B6: =B4-B5 | D6: Travel | E6: =SUMIFS(Transactions!E:E,Transactions!B:B,D6,Transactions!C:C,"Income") | F6: =SUMIFS(Transactions!E:E,Transactions!B:B,D6,Transactions!C:C,"Expense") | G6: =E6-F6
A7: Profit Margin % | B7: =IFERROR(B6/B4,0) | D7: Textile | E7: =SUMIFS(Transactions!E:E,Transactions!B:B,D7,Transactions!C:C,"Income") | F7: =SUMIFS(Transactions!E:E,Transactions!B:B,D7,Transactions!C:C,"Expense") | G7: =E7-F7
A8: Monthly Growth % (Mar vs Feb 2026) | B8: =IFERROR((SUMIFS(Transactions!E:E,Transactions!F:F,"Mar-26",Transactions!C:C,"Income")-SUMIFS(Transactions!E:E,Transactions!F:F,"Mar-26",Transactions!C:C,"Expense")-(SUMIFS(Transactions!E:E,Transactions!F:F,"Feb-26",Transactions!C:C,"Income")-SUMIFS(Transactions!E:E,Transactions!F:F,"Feb-26",Transactions!C:C,"Expense")))/ABS(SUMIFS(Transactions!E:E,Transactions!F:F,"Feb-26",Transactions!C:C,"Income")-SUMIFS(Transactions!E:E,Transactions!F:F,"Feb-26",Transactions!C:C,"Expense")),0) | D8: Hardware | E8: =SUMIFS(Transactions!E:E,Transactions!B:B,D8,Transactions!C:C,"Income") | F8: =SUMIFS(Transactions!E:E,Transactions!B:B,D8,Transactions!C:C,"Expense") | G8: =E8-F8
A11: Expense by Category | D11: Monthly Trend
A12: Category | B12: Expense (INR) | D12: Month | E12: Income (INR) | F12: Expense (INR) | G12: Profit (INR)
A13: Fuel | B13: =SUMIFS(Transactions!E:E,Transactions!D:D,A13,Transactions!C:C,"Expense") | D13: Dec-25 | E13: =SUMIFS(Transactions!E:E,Transactions!F:F,D13,Transactions!C:C,"Income") | F13: =SUMIFS(Transactions!E:E,Transactions!F:F,D13,Transactions!C:C,"Expense") | G13: =E13-F13
A14: Inventory | B14: =SUMIFS(Transactions!E:E,Transactions!D:D,A14,Transactions!C:C,"Expense") | D14: Jan-26 | E14: =SUMIFS(Transactions!E:E,Transactions!F:F,D14,Transactions!C:C,"Income") | F14: =SUMIFS(Transactions!E:E,Transactions!F:F,D14,Transactions!C:C,"Expense") | G14: =E14-F14
A15: Supplies | B15: =SUMIFS(Transactions!E:E,Transactions!D:D,A15,Transactions!C:C,"Expense") | D15: Feb-26 | E15: =SUMIFS(Transactions!E:E,Transactions!F:F,D15,Transactions!C:C,"Income") | F15: =SUMIFS(Transactions!E:E,Transactions!F:F,D15,Transactions!C:C,"Expense") | G15: =E15-F15
A16: Logistics | B16: =SUMIFS(Transactions!E:E,Transactions!D:D,A16,Transactions!C:C,"Expense") | D16: Mar-26 | E16: =SUMIFS(Transactions!E:E,Transactions!F:F,D16,Transactions!C:C,"Income") | F16: =SUMIFS(Transactions!E:E,Transactions!F:F,D16,Transactions!C:C,"Expense") | G16: =E16-F16
A17: Marketing | B17: =SUMIFS(Transactions!E:E,Transactions!D:D,A17,Transactions!C:C,"Expense")
A18: Rent | B18: =SUMIFS(Transactions!E:E,Transactions!D:D,A18,Transactions!C:C,"Expense")
A19: Utilities | B19: =SUMIFS(Transactions!E:E,Transactions!D:D,A19,Transactions!C:C,"Expense")
A20: Payroll | B20: =SUMIFS(Transactions!E:E,Transactions!D:D,A20,Transactions!C:C,"Expense")
A21: Maintenance | B21: =SUMIFS(Transactions!E:E,Transactions!D:D,A21,Transactions!C:C,"Expense")

Sheet Charts
A1: Visual Dashboard
